[
  {
    "id": 1746435182422,
    "name": "Wickelauflage",
    "quantity": "500",
    "price": "44.95",
    "location": "Hamburg"
  },
  {
    "id": 1746435250497,
    "name": "Hüftsitz",
    "quantity": "500",
    "price": "34.95",
    "location": "Hamburg"
  },
  {
    "id": 1746435307963,
    "name": "Hundebett",
    "quantity": "500",
    "price": "20.00",
    "location": "Hamburg"
  },
  {
    "id": 1746437775644,
    "name": "Gummiauflage",
    "quantity": "500",
    "price": "9.95",
    "location": "Hamburg"
  },
  {
    "id": 1746437802503,
    "name": "Deichselhaube",
    "quantity": "500",
    "price": "14.95",
    "location": "Hamburg"
  }
]